{
    "images": [
        { "name": "textura_chao",   "path": "DemoMiniGame3D/Assets/Textures/floor.jpg"},
        { "name": "textura_player", "path": "DemoMiniGame3D/Assets/Textures/player.jpg" },
        { "name": "textura_coin",   "path": "DemoMiniGame3D/Assets/Textures/coin.jpg"},
        { "name": "sky_cross",      "path": "DemoMiniGame3D/Assets/Textures/Daylight Box UV.png"}
    ],
    "audios": [
        { "name": "bgm_fase1",  "path": "DemoAdvanced/Assets/BGM/battle_sound.mpeg" },
        { "name": "sfx_jump",   "path": "DemoAdvanced/Assets/SFX/jump 1.wav" },
        { "name": "sfx_laser",  "path": "DemoAdvanced/Assets/SFX/Blow 1V2.wav" }
    ],
    "shaders": [
        { "name": "vertexShader",       "path": "Shaders/VertexShader.glsl"},
        { "name": "fragmentShader",     "path": "Shaders/FragmentShader.glsl"},
        { "name": "MeshFragmentShader", "path": "Shaders/MeshFragmentShader.glsl" },
        { "name": "MeshVertexShader",   "path": "Shaders/MeshVertexShader.glsl" },
        { "name": "SkyFragmentShader",  "path": "Shaders/SkyBoxFragmentShader.glsl" },
        { "name": "SkyVertexShader",    "path": "Shaders/SkyBoxVertexShader.glsl" }
    ],
    "models": [
        {"name": "character", "path": "DemoMiniGame3D/Assets/Models/character.glb"}
    ]
}